omniai/__init__.py
omniai/main.py
omniai/core/__init__.py
omniai/core/advisor.py
omniai/core/advisor_backup_20251226_190025.py
omniai/core/analyze_core.py
omniai/core/check_deps.py
omniai/core/cleaner.py
omniai/core/full_analysis.py
omniai/core/omni_ai_pipeline.py
omniai/core/omni_pipeline_fixed.py
omniai/core/run_omni_ai.py
omniai/core/simple_check.py
omniai/core/test_api.py
omniai/domains/__init__.py
omniai/domains/medical/__init__.py
omniai/domains/medical/medical_processor.py
omniai/engine/__init__.py
omniai/engine/dask_engine.py
omniai/utils/__init__.py
omniai/utils/file_handler.py
omniai_lakshya-2.0.4.dist-info/METADATA
omniai_lakshya-2.0.4.dist-info/WHEEL
omniai_lakshya-2.0.4.dist-info/top_level.txt
omniai_lakshya-2.0.4.dist-info/RECORD
