Metadata-Version: 2.4
Name: omniai-lakshya
Version: 2.0.4
Summary: OmniAI - Complete AutoML Pipeline with 52+ algorithms
Author: Lakshya Gupta
Author-email: lakshyagupta1040@gmail.com
Requires-Dist: pandas>=1.0
Requires-Dist: numpy>=1.19
Dynamic: author
Dynamic: author-email
Dynamic: requires-dist
Dynamic: summary
